pydast/Disjoint_Set.py
pydast/Graphs.py
pydast/Heaps.py
pydast/LinkedList.py
pydast/Trees.py
pydast/Trie.py
pydast/_Heaps.py
pydast/_Trie.py
pydast/__init__.py
pydast-0.0.1.dist-info/Licence.txt
pydast-0.0.1.dist-info/METADATA
pydast-0.0.1.dist-info/WHEEL
pydast-0.0.1.dist-info/top_level.txt
pydast-0.0.1.dist-info/RECORD
