Metadata-Version: 2.1
Name: pydast
Version: 0.0.1
Summary: Python package providing powerful Data Structures for use
Home-page: https://github.com/ThinkWithKush/PyDaSt
Author: Kushagra Agarwal
Author-email: kushagra.agarwal.2709@gmail.com
License: UNKNOWN
Platform: UNKNOWN
Classifier: Programming Language :: Python :: 3
Classifier: Operating System :: OS Independent
License-File: Licence.txt
